{
  "openapi": "3.0.1",
  "info": {
    "title": "ControlGastosBackend",
    "version": "1.0"
  },
  "paths": {
    "/api/FondoMonetario": {
      "post": {
        "tags": [
          "FondoMonetario"
        ],
        "requestBody": {
          "content": {
            "application/json": {
              "schema": {
                "$ref": "#/components/schemas/CrearFondoMonetarioDTO"
              }
            },
            "text/json": {
              "schema": {
                "$ref": "#/components/schemas/CrearFondoMonetarioDTO"
              }
            },
            "application/*+json": {
              "schema": {
                "$ref": "#/components/schemas/CrearFondoMonetarioDTO"
              }
            }
          }
        },
        "responses": {
          "200": {
            "description": "OK"
          }
        }
      },
      "get": {
        "tags": [
          "FondoMonetario"
        ],
        "responses": {
          "200": {
            "description": "OK"
          }
        }
      }
    },
    "/api/Movimiento": {
      "post": {
        "tags": [
          "Movimiento"
        ],
        "requestBody": {
          "content": {
            "application/json": {
              "schema": {
                "$ref": "#/components/schemas/CrearMovimientoDTO"
              }
            },
            "text/json": {
              "schema": {
                "$ref": "#/components/schemas/CrearMovimientoDTO"
              }
            },
            "application/*+json": {
              "schema": {
                "$ref": "#/components/schemas/CrearMovimientoDTO"
              }
            }
          }
        },
        "responses": {
          "200": {
            "description": "OK"
          }
        }
      }
    },
    "/api/PresupuestoGasto": {
      "post": {
        "tags": [
          "PresupuestoGasto"
        ],
        "requestBody": {
          "content": {
            "application/json": {
              "schema": {
                "$ref": "#/components/schemas/PresupuestoGastoCreateDto"
              }
            },
            "text/json": {
              "schema": {
                "$ref": "#/components/schemas/PresupuestoGastoCreateDto"
              }
            },
            "application/*+json": {
              "schema": {
                "$ref": "#/components/schemas/PresupuestoGastoCreateDto"
              }
            }
          }
        },
        "responses": {
          "200": {
            "description": "OK"
          }
        }
      }
    },
    "/api/PresupuestoGasto/{id}/anioMes/{anioMes}": {
      "get": {
        "tags": [
          "PresupuestoGasto"
        ],
        "parameters": [
          {
            "name": "id",
            "in": "path",
            "required": true,
            "schema": {
              "type": "string",
              "format": "uuid"
            }
          },
          {
            "name": "anioMes",
            "in": "path",
            "required": true,
            "schema": {
              "type": "string"
            }
          }
        ],
        "responses": {
          "200": {
            "description": "OK"
          }
        }
      }
    },
    "/api/RegistroGasto": {
      "post": {
        "tags": [
          "RegistroGasto"
        ],
        "requestBody": {
          "content": {
            "application/json": {
              "schema": {
                "$ref": "#/components/schemas/RegistroGastoCreateDto"
              }
            },
            "text/json": {
              "schema": {
                "$ref": "#/components/schemas/RegistroGastoCreateDto"
              }
            },
            "application/*+json": {
              "schema": {
                "$ref": "#/components/schemas/RegistroGastoCreateDto"
              }
            }
          }
        },
        "responses": {
          "200": {
            "description": "OK"
          }
        }
      },
      "get": {
        "tags": [
          "RegistroGasto"
        ],
        "responses": {
          "200": {
            "description": "OK"
          }
        }
      }
    },
    "/api/RegistroGasto/{id}": {
      "get": {
        "tags": [
          "RegistroGasto"
        ],
        "parameters": [
          {
            "name": "id",
            "in": "path",
            "required": true,
            "schema": {
              "type": "string",
              "format": "uuid"
            }
          }
        ],
        "responses": {
          "200": {
            "description": "OK"
          }
        }
      }
    },
    "/api/TipoGasto": {
      "post": {
        "tags": [
          "TipoGasto"
        ],
        "requestBody": {
          "content": {
            "application/json": {
              "schema": {
                "$ref": "#/components/schemas/CreateTipoGastoDto"
              }
            },
            "text/json": {
              "schema": {
                "$ref": "#/components/schemas/CreateTipoGastoDto"
              }
            },
            "application/*+json": {
              "schema": {
                "$ref": "#/components/schemas/CreateTipoGastoDto"
              }
            }
          }
        },
        "responses": {
          "200": {
            "description": "OK"
          }
        }
      },
      "get": {
        "tags": [
          "TipoGasto"
        ],
        "responses": {
          "200": {
            "description": "OK"
          }
        }
      }
    }
  },
  "components": {
    "schemas": {
      "CrearFondoMonetarioDTO": {
        "type": "object",
        "properties": {
          "nombre": {
            "type": "string",
            "nullable": true
          },
          "descripcion": {
            "type": "string",
            "nullable": true
          },
          "tipo": {
            "type": "integer",
            "format": "int32"
          },
          "saldoActual": {
            "type": "number",
            "format": "double"
          }
        },
        "additionalProperties": false
      },
      "CrearMovimientoDTO": {
        "type": "object",
        "properties": {
          "fecha": {
            "type": "string",
            "format": "date-time"
          },
          "descripcion": {
            "type": "string",
            "nullable": true
          },
          "tipo": {
            "$ref": "#/components/schemas/TipoMovimiento"
          },
          "monto": {
            "type": "number",
            "format": "double"
          }
        },
        "additionalProperties": false
      },
      "CreateTipoGastoDto": {
        "type": "object",
        "properties": {
          "nombre": {
            "type": "string",
            "nullable": true
          },
          "descripcion": {
            "type": "string",
            "nullable": true
          },
          "color": {
            "type": "string",
            "nullable": true
          }
        },
        "additionalProperties": false
      },
      "PresupuestoGastoCreateDto": {
        "type": "object",
        "properties": {
          "tipoGastoId": {
            "type": "string",
            "format": "uuid"
          },
          "monto": {
            "type": "number",
            "format": "double"
          },
          "montoEjecutado": {
            "type": "number",
            "format": "double"
          },
          "anioMes": {
            "type": "string",
            "nullable": true
          }
        },
        "additionalProperties": false
      },
      "RegistroGastoCreateDto": {
        "type": "object",
        "properties": {
          "fecha": {
            "type": "string",
            "format": "date-time"
          },
          "fondoMonetarioId": {
            "type": "string",
            "format": "uuid"
          },
          "observaciones": {
            "type": "string",
            "nullable": true
          },
          "nombreComercio": {
            "type": "string",
            "nullable": true
          },
          "tipoDocumento": {
            "type": "integer",
            "format": "int32"
          },
          "detalles": {
            "type": "array",
            "items": {
              "$ref": "#/components/schemas/RegistroGastoDetalleCreateDto"
            },
            "nullable": true
          }
        },
        "additionalProperties": false
      },
      "RegistroGastoDetalleCreateDto": {
        "type": "object",
        "properties": {
          "tipoGastoId": {
            "type": "string",
            "format": "uuid"
          },
          "monto": {
            "type": "number",
            "format": "double"
          },
          "descripcion": {
            "type": "string",
            "nullable": true
          }
        },
        "additionalProperties": false
      },
      "TipoMovimiento": {
        "enum": [
          1,
          2
        ],
        "type": "integer",
        "format": "int32"
      }
    }
  }
}